wtforglib/__init__.py
wtforglib/commander.py
wtforglib/constants.py
wtforglib/dirs.py
wtforglib/errors.py
wtforglib/files.py
wtforglib/fstats.py
wtforglib/functions.py
wtforglib/ipaddress_foos.py
wtforglib/kinds.py
wtforglib/options.py
wtforglib/py.typed
wtforglib/singles.py
wtforglib/supers.py
wtforglib/tmplwrtr.py
wtforglib/ugpw.py
wtforglib/validators.py
wtforglib/versioned.py
wtforglib/versionfile.py
wtforglib-1.3.0.dist-info/LICENSE
wtforglib-1.3.0.dist-info/METADATA
wtforglib-1.3.0.dist-info/WHEEL
wtforglib-1.3.0.dist-info/RECORD
