Metadata-Version: 2.3
Name: wtforglib
Version: 1.3.0
Summary: A set of utility functions I use in my various python projects.
License: MIT
Author: Quien Sabe
Author-email: qs5779@mail.com
Requires-Python: >=3.10,<4.0
Classifier: Development Status :: 4 - Beta
Classifier: Intended Audience :: Developers
Classifier: License :: OSI Approved :: MIT License
Classifier: Operating System :: OS Independent
Classifier: Programming Language :: Python :: 3
Classifier: Programming Language :: Python :: 3.10
Classifier: Programming Language :: Python :: 3.11
Classifier: Programming Language :: Python :: 3.12
Classifier: Programming Language :: Python :: 3.13
Classifier: Programming Language :: Python :: 3 :: Only
Classifier: Topic :: Software Development :: Libraries :: Python Modules
Classifier: Typing :: Typed
Requires-Dist: jinja2 (>=3.1.2,<4.0.0)
Requires-Dist: pyyaml (>=6.0,<7.0)
Requires-Dist: types-pyyaml (>=6.0.12,<7.0.0)
Project-URL: Documentation, https://wtforglib.readthedocs.io/en/stable
Project-URL: Homepage, https://github.com/wtfo-guru/wtforglib
